README.md
setup.py
lambdautils/__init__.py
lambdautils/exception.py
lambdautils/kinesis.py
lambdautils/monitor.py
lambdautils/state.py
lambdautils/utils.py
lambdautils.egg-info/PKG-INFO
lambdautils.egg-info/SOURCES.txt
lambdautils.egg-info/dependency_links.txt
lambdautils.egg-info/not-zip-safe
lambdautils.egg-info/requires.txt
lambdautils.egg-info/top_level.txt