Metadata-Version: 1.1
Name: lambdautils
Version: 1.6.2
Summary: Utilities for AWS Lambda functions
Home-page: https://github.com/humilis/humilis-lambdautils
Author: German Gomez-Herrero, Arnaud Charpentier, FindHotel BV
Author-email: german@findhotel.net
License: MIT
Platform: UNKNOWN
Classifier: Programming Language :: Python :: 2.7
